MANIFEST.in
README.rst
setup.cfg
setup.py
ckanext/__init__.py
ckanext/ddugtheme/__init__.py
ckanext/ddugtheme/plugin.py
ckanext/ddugtheme/tests/__init__.py
ckanext/ddugtheme/tests/test_plugin.py
ckanext_ddugtheme.egg-info/PKG-INFO
ckanext_ddugtheme.egg-info/SOURCES.txt
ckanext_ddugtheme.egg-info/dependency_links.txt
ckanext_ddugtheme.egg-info/entry_points.txt
ckanext_ddugtheme.egg-info/pbr.json
ckanext_ddugtheme.egg-info/top_level.txt