Metadata-Version: 1.1
Name: ckanext-ddugtheme
Version: 0.0.1
Summary: Theme for datadotug
Home-page: https://github.com/datadotug/ckanext-ddugtheme
Author: Dan Mulindwa
Author-email: dmulindwa@gmail.com
License: AGPL
Keywords: CKAN Datadotug theme
Platform: UNKNOWN
Classifier: Development Status :: 4 - Beta
Classifier: License :: OSI Approved :: GNU Affero General Public License v3 or later (AGPLv3+)
Classifier: Programming Language :: Python :: 2.6
Classifier: Programming Language :: Python :: 2.7
